Elasticipy/FourthOrderTensor.py
Elasticipy/StressStrainTensors.py
Elasticipy/ThermalExpansion.py
Elasticipy/__init__.py
Elasticipy/crystal_symmetries.py
Elasticipy/gui.py
Elasticipy/plasticity.py
Elasticipy/polefigure.py
Elasticipy/spherical_function.py
Elasticipy/interfaces/FEPX.py
Elasticipy/interfaces/PRISMS.py
Elasticipy/tensors/__init__.py
Elasticipy/tensors/elasticity.py
Elasticipy/tensors/fourth_order.py
Elasticipy/tensors/mapping.py
Elasticipy/tensors/second_order.py
Elasticipy/tensors/stress_strain.py
Elasticipy/tensors/thermal_expansion.py
elasticipy-5.0.0.dist-info/licenses/LICENSE
elasticipy-5.0.0.dist-info/METADATA
elasticipy-5.0.0.dist-info/WHEEL
elasticipy-5.0.0.dist-info/entry_points.txt
elasticipy-5.0.0.dist-info/top_level.txt
elasticipy-5.0.0.dist-info/RECORD
