Metadata-Version: 2.4
Name: elasticipy
Version: 5.0.0
Summary: A Python library for elasticity tensor computations
Author-email: Dorian Depriester <dorian.dep@gmail.com>
License: MIT
Project-URL: Homepage, https://pypi.org/project/Elasticipy/
Project-URL: Source, https://github.com/DorianDepriester/Elasticipy
Project-URL: Tracker, https://github.com/DorianDepriester/Elasticipy/issues
Project-URL: Documentation, https://elasticipy.readthedocs.io/
Classifier: Development Status :: 4 - Beta
Classifier: Intended Audience :: Science/Research
Classifier: License :: OSI Approved :: MIT License
Classifier: Programming Language :: Python
Classifier: Programming Language :: Python :: 3.9
Classifier: Programming Language :: Python :: 3.10
Classifier: Programming Language :: Python :: 3.11
Classifier: Programming Language :: Python :: 3.12
Requires-Python: >=3.9
License-File: LICENSE
Requires-Dist: numpy>=1.20.0
Requires-Dist: scipy
Requires-Dist: matplotlib
Requires-Dist: qtpy
Requires-Dist: pyqt5
Requires-Dist: pandas
Provides-Extra: dev
Requires-Dist: pytest; extra == "dev"
Requires-Dist: pytest-cov; extra == "dev"
Requires-Dist: pymatgen; extra == "dev"
Requires-Dist: orix; extra == "dev"
Requires-Dist: mp_api==0.45.9; extra == "dev"
Dynamic: license-file
